aisecurity/__init__.py
aisecurity/configuration.py
aisecurity/exceptions.py
aisecurity/logger.py
aisecurity/utils.py
aisecurity/constants/__init__.py
aisecurity/constants/base.py
aisecurity/generated_openapi_client/.ruff.toml
aisecurity/generated_openapi_client/__init__.py
aisecurity/generated_openapi_client/models_changes.md
aisecurity/generated_openapi_client/asyncio/__init__.py
aisecurity/generated_openapi_client/asyncio/api_client.py
aisecurity/generated_openapi_client/asyncio/api_response.py
aisecurity/generated_openapi_client/asyncio/configuration.py
aisecurity/generated_openapi_client/asyncio/exceptions.py
aisecurity/generated_openapi_client/asyncio/py.typed
aisecurity/generated_openapi_client/asyncio/rest.py
aisecurity/generated_openapi_client/asyncio/api/__init__.py
aisecurity/generated_openapi_client/asyncio/api/internal_health_check_api.py
aisecurity/generated_openapi_client/asyncio/api/scan_reports_api.py
aisecurity/generated_openapi_client/asyncio/api/scan_results_api.py
aisecurity/generated_openapi_client/asyncio/api/scans_api.py
aisecurity/generated_openapi_client/models/__init__.py
aisecurity/generated_openapi_client/models/agent_entry_object.py
aisecurity/generated_openapi_client/models/agent_meta.py
aisecurity/generated_openapi_client/models/agent_report_object.py
aisecurity/generated_openapi_client/models/ai_profile.py
aisecurity/generated_openapi_client/models/async_scan_object.py
aisecurity/generated_openapi_client/models/async_scan_response.py
aisecurity/generated_openapi_client/models/cg_report_object.py
aisecurity/generated_openapi_client/models/cmd_entry_object.py
aisecurity/generated_openapi_client/models/dbs_entry_object.py
aisecurity/generated_openapi_client/models/detection_service_result_object.py
aisecurity/generated_openapi_client/models/dlp_pattern_detections_object.py
aisecurity/generated_openapi_client/models/dlp_report_object.py
aisecurity/generated_openapi_client/models/ds_detail_result_object.py
pan_aisecurity-0.8.0.5.post2.dist-info/METADATA
pan_aisecurity-0.8.0.5.post2.dist-info/WHEEL
pan_aisecurity-0.8.0.5.post2.dist-info/licenses/LICENSE
pan_aisecurity-0.8.0.5.post2.dist-info/RECORD
