Metadata-Version: 2.4
Name: pan-aisecurity
Version: 0.8.0.5.post2
Summary: Palo Alto Networks AI Runtime Security: API Intercept Python SDK
Project-URL: Homepage, https://www.paloaltonetworks.com/prisma/prisma-ai-runtime-security
Project-URL: Documentation, https://pan.dev/ai-runtime-security/scan/api/
Author-email: Palo Alto Networks AI Runtime Security SDK Team <dl-airs-api-sdk@paloaltonetworks.com>
License-File: LICENSE
Keywords: AI Runtime Security,AI Security,Palo Alto Networks,PaloAltoNetworks
Classifier: Development Status :: 4 - Beta
Classifier: Intended Audience :: Developers
Classifier: License :: Other/Proprietary License
Classifier: Natural Language :: English
Classifier: Programming Language :: Python :: 3
Classifier: Topic :: Scientific/Engineering :: Artificial Intelligence
Classifier: Typing :: Typed
Requires-Python: >=3.9
Requires-Dist: aiodns>=1.1
Requires-Dist: aiohttp-retry~=2.9
Requires-Dist: aiohttp~=3.11
Requires-Dist: arrow~=1.3
Requires-Dist: lazy-imports>=1
Requires-Dist: pydantic>=2
Requires-Dist: python-dateutil~=2.8
Requires-Dist: singleton-decorator~=1.0
Requires-Dist: typing-extensions~=4.7
Requires-Dist: urllib3~=2.2
Provides-Extra: docs
Requires-Dist: readme-renderer[md]>=44.0; extra == 'docs'
Provides-Extra: mcp
Requires-Dist: fastmcp>=2.5.2; (python_full_version >= '3.10') and extra == 'mcp'
Requires-Dist: mcp>=1.9.2; (python_full_version >= '3.10') and extra == 'mcp'
Provides-Extra: test
Requires-Dist: coverage-enable-subprocess>=1.0; extra == 'test'
Requires-Dist: coverage[toml]; extra == 'test'
Requires-Dist: mypy>=1.5; extra == 'test'
Requires-Dist: pyright[nodejs]>=1.1.401; extra == 'test'
Requires-Dist: pytest-asyncio>=1.0.0; extra == 'test'
Requires-Dist: pytest-cov>=6.0; extra == 'test'
Requires-Dist: pytest-mock>=3.14.1; extra == 'test'
Requires-Dist: pytest-randomly>=3.16.0; extra == 'test'
Requires-Dist: pytest-rerunfailures>=15.1; extra == 'test'
Requires-Dist: pytest-xdist[psutil]>=3.7.0; extra == 'test'
Requires-Dist: pytest>=8.3.5; extra == 'test'
